[
  {
    "symbol": "CPOOL",
    "chain": "multi",
    "dex": "uniswap_v3",
    "pool_address": "0x81aee07f99be78d88881fa6d98feff7555113635",
    "pair": "CPOOL / USDC 0.3%",
    "price_usd": 0.034331458482232,
    "lp_reserve_usd": 132258.8982,
    "volume_24h": 140984.153874448,
    "fee_tier": null,
    "source": "geckoterminal",
    "timestamp": 1767009543
  },
  {
    "symbol": "CPOOL",
    "chain": "multi",
    "dex": "uniswap-v4-ethereum",
    "pool_address": "0x60790069a28eaf821b39e4829d6490f4bda65aece51192df8f8ead512435bda6",
    "pair": "CPOOL / ETH 1%",
    "price_usd": 0.0344545721064005,
    "lp_reserve_usd": 26561.9377,
    "volume_24h": 28900.1039271429,
    "fee_tier": null,
    "source": "geckoterminal",
    "timestamp": 1767009543
  },
  {
    "symbol": "CPOOL",
    "chain": "multi",
    "dex": "raydium-clmm",
    "pool_address": "EWNQDcSyA38ynQfwZVMr237Hytb1VsfvY54S1hEth3i6",
    "pair": "CPOOL / SOL",
    "price_usd": 0.034791455839848884,
    "lp_reserve_usd": 11452.013,
    "volume_24h": 7051.6225360431,
    "fee_tier": null,
    "source": "geckoterminal",
    "timestamp": 1767009543
  }
]