[
  {
    "symbol": "ong",
    "chain": "solana",
    "dex": "raydium",
    "pool_address": "8p7SxnBgw9hghfKnADeKGXDUBDm5L3M24Zd1yzXPuu7m",
    "pair": "ONG/USD",
    "price_usd": 0.00002486,
    "lp_reserve_usd": 30335.14,
    "volume_24h": 1.21,
    "fee_tier": null,
    "source": "dexscreener",
    "timestamp": 1767096064
  },
  {
    "symbol": "ong",
    "chain": "solana",
    "dex": "pumpfun",
    "pool_address": "Xx95WPcjqSWc6eNYLqbPRgBh1Afieqzopwy9H18DFo9",
    "pair": "ONG/USD",
    "price_usd": 3.458e-6,
    "lp_reserve_usd": 0.0,
    "volume_24h": 0.01,
    "fee_tier": null,
    "source": "dexscreener",
    "timestamp": 1767096064
  }
]