[
  {
    "symbol": "PLUME",
    "chain": "solana",
    "dex": "raydium",
    "pool_address": "qpG9Vvpuh9eGew31R3sfDvxbmFLJrmFxALRmMQzNosH",
    "pair": "PLUME/USD",
    "price_usd": 0.1138,
    "lp_reserve_usd": 1137024624.5,
    "volume_24h": 7.99,
    "fee_tier": null,
    "source": "dexscreener",
    "timestamp": 1767096144
  },
  {
    "symbol": "PLUME",
    "chain": "multi",
    "dex": "uniswap_v2",
    "pool_address": "0x2d6c94c97f7944b35372270339d9f944cd11b2d8",
    "pair": "PLUME / WETH",
    "price_usd": 0.0166741777164052,
    "lp_reserve_usd": 2953.0811,
    "volume_24h": 552.3718313507,
    "fee_tier": null,
    "source": "geckoterminal",
    "timestamp": 1767096149
  },
  {
    "symbol": "PLUME",
    "chain": "solana",
    "dex": "orca",
    "pool_address": "GGrHmWyX2muit2sXuxKJ2uM5yBAUgVBJpfAPzth5Qdb1",
    "pair": "PLUME/USD",
    "price_usd": 0.103,
    "lp_reserve_usd": 1029546285.44,
    "volume_24h": 3.99,
    "fee_tier": null,
    "source": "dexscreener",
    "timestamp": 1767096144
  },
  {
    "symbol": "PLUME",
    "chain": "ethereum",
    "dex": "uniswap",
    "pool_address": "0x2D6c94c97f7944b35372270339d9F944Cd11b2d8",
    "pair": "PLUME/USD",
    "price_usd": 0.01667,
    "lp_reserve_usd": 2950.58,
    "volume_24h": 553.32,
    "fee_tier": null,
    "source": "dexscreener",
    "timestamp": 1767096144
  },
  {
    "symbol": "PLUME",
    "chain": "multi",
    "dex": "raydium-clmm",
    "pool_address": "qpG9Vvpuh9eGew31R3sfDvxbmFLJrmFxALRmMQzNosH",
    "pair": "PLUME / USDC",
    "price_usd": 0.11362965756840702,
    "lp_reserve_usd": 1133571664.6843,
    "volume_24h": 7.9864993945,
    "fee_tier": null,
    "source": "geckoterminal",
    "timestamp": 1767096149
  },
  {
    "symbol": "PLUME",
    "chain": "multi",
    "dex": "uniswap_v3",
    "pool_address": "0xe35bfbf439d7c37e2df41bf1236ccf1dec0543fd",
    "pair": "PLUME / USDC 1%",
    "price_usd": 0.017079321626245,
    "lp_reserve_usd": 25098.076,
    "volume_24h": 100.3158719418,
    "fee_tier": null,
    "source": "geckoterminal",
    "timestamp": 1767096149
  },
  {
    "symbol": "PLUME",
    "chain": "multi",
    "dex": "rooster-protocol-v2",
    "pool_address": "0xdcd87e7f2cb5b488506768ac97e4041dd16f8c94",
    "pair": "WPLUME / WETH 0.05%",
    "price_usd": 0.01676682,
    "lp_reserve_usd": 93369.0921,
    "volume_24h": 11424.6297487399,
    "fee_tier": null,
    "source": "geckoterminal",
    "timestamp": 1767096149
  },
  {
    "symbol": "PLUME",
    "chain": "solana",
    "dex": "pumpswap",
    "pool_address": "8Sg8pNRjtWpDnYraRLATzpYjJbBwc9NFMrhH8ZHcxeU1",
    "pair": "PLUME/USD",
    "price_usd": 0.01676,
    "lp_reserve_usd": 138113.77,
    "volume_24h": 2442.78,
    "fee_tier": null,
    "source": "dexscreener",
    "timestamp": 1767096144
  },
  {
    "symbol": "PLUME",
    "chain": "multi",
    "dex": "rooster-protocol",
    "pool_address": "0x39ba3c1dbe665452e86fde9c71fc64c78aa2445c",
    "pair": "pUSD / WPLUME 0.3%",
    "price_usd": 0.904161059374495,
    "lp_reserve_usd": 186502.2534,
    "volume_24h": 0.7669592457,
    "fee_tier": null,
    "source": "geckoterminal",
    "timestamp": 1767096149
  },
  {
    "symbol": "PLUME",
    "chain": "solana",
    "dex": "orca",
    "pool_address": "9V6pWMkKWb5s4b1XcPPgifBPZUsxD98E61JDKydfvHMt",
    "pair": "PLUME/USD",
    "price_usd": 0.0005889,
    "lp_reserve_usd": 23250.03,
    "volume_24h": 0.12,
    "fee_tier": null,
    "source": "dexscreener",
    "timestamp": 1767096144
  },
  {
    "symbol": "PLUME",
    "chain": "ethereum",
    "dex": "uniswap",
    "pool_address": "0xf0cd01da66753629340436cee3b26dc4a7d63cbee01e2f2d7c8230a8210526cc",
    "pair": "PLUME/USD",
    "price_usd": 0.01684,
    "lp_reserve_usd": 380013.0,
    "volume_24h": 113.5,
    "fee_tier": null,
    "source": "dexscreener",
    "timestamp": 1767096144
  },
  {
    "symbol": "PLUME",
    "chain": "multi",
    "dex": "curve-plume",
    "pool_address": "0xceaf9a74cb507206608d0c7fec23a3dcd47f2c6c",
    "pair": "pUSD / WPLUME",
    "price_usd": 1.02437322755627,
    "lp_reserve_usd": 1001.7187,
    "volume_24h": 251.0274493487,
    "fee_tier": null,
    "source": "geckoterminal",
    "timestamp": 1767096149
  },
  {
    "symbol": "PLUME",
    "chain": "multi",
    "dex": "pumpswap",
    "pool_address": "8Sg8pNRjtWpDnYraRLATzpYjJbBwc9NFMrhH8ZHcxeU1",
    "pair": "PLUME / USDC",
    "price_usd": 0.016772967371466625,
    "lp_reserve_usd": 137963.0558,
    "volume_24h": 2492.6271555199,
    "fee_tier": null,
    "source": "geckoterminal",
    "timestamp": 1767096149
  },
  {
    "symbol": "PLUME",
    "chain": "multi",
    "dex": "rooster-protocol-v2",
    "pool_address": "0x05acf22149bb67a682e652674b6901f02cb57731",
    "pair": "pUSD / WPLUME 0.1%",
    "price_usd": 0.995494290380832,
    "lp_reserve_usd": 111176.5104,
    "volume_24h": 22861.1200272429,
    "fee_tier": null,
    "source": "geckoterminal",
    "timestamp": 1767096149
  },
  {
    "symbol": "PLUME",
    "chain": "multi",
    "dex": "orca",
    "pool_address": "GGrHmWyX2muit2sXuxKJ2uM5yBAUgVBJpfAPzth5Qdb1",
    "pair": "PLUME / USDC",
    "price_usd": 0.10283136699589769,
    "lp_reserve_usd": 1038743191.2184,
    "volume_24h": 3.9871933059,
    "fee_tier": null,
    "source": "geckoterminal",
    "timestamp": 1767096149
  },
  {
    "symbol": "PLUME",
    "chain": "ethereum",
    "dex": "uniswap",
    "pool_address": "0xe35Bfbf439D7C37E2Df41BF1236cCf1dEc0543fd",
    "pair": "PLUME/USD",
    "price_usd": 0.01689,
    "lp_reserve_usd": 24854.78,
    "volume_24h": 100.27,
    "fee_tier": null,
    "source": "dexscreener",
    "timestamp": 1767096144
  },
  {
    "symbol": "PLUME",
    "chain": "ethereum",
    "dex": "uniswap",
    "pool_address": "0xD845AcDeb03fB3295E7735C232C588efc441D903",
    "pair": "PLUME/USD",
    "price_usd": 0.0169,
    "lp_reserve_usd": 18050.52,
    "volume_24h": 8677.36,
    "fee_tier": null,
    "source": "dexscreener",
    "timestamp": 1767096144
  },
  {
    "symbol": "PLUME",
    "chain": "multi",
    "dex": "uniswap_v3",
    "pool_address": "0xd845acdeb03fb3295e7735c232c588efc441d903",
    "pair": "PLUME / WETH 1%",
    "price_usd": 0.0167414299936661,
    "lp_reserve_usd": 18164.3047,
    "volume_24h": 8749.5702735204,
    "fee_tier": null,
    "source": "geckoterminal",
    "timestamp": 1767096149
  },
  {
    "symbol": "PLUME",
    "chain": "multi",
    "dex": "uniswap-v4-ethereum",
    "pool_address": "0xf0cd01da66753629340436cee3b26dc4a7d63cbee01e2f2d7c8230a8210526cc",
    "pair": "PLUME / USDC 1%",
    "price_usd": 0.0170092470373894,
    "lp_reserve_usd": 554201.8434,
    "volume_24h": 106.4712967625,
    "fee_tier": null,
    "source": "geckoterminal",
    "timestamp": 1767096149
  }
]