[
  {
    "symbol": "SHIB",
    "chain": "multi",
    "dex": "pancakeswap-v3-bsc",
    "pool_address": "0xe8df1539b380274f1f8205a8f45a7cc266793518",
    "pair": "SHIB / WBNB 0.25%",
    "price_usd": 7.17484170571728e-6,
    "lp_reserve_usd": 84015.8609,
    "volume_24h": 22163.6774915368,
    "fee_tier": null,
    "source": "geckoterminal",
    "timestamp": 1767060374
  },
  {
    "symbol": "SHIB",
    "chain": "multi",
    "dex": "uniswap_v2",
    "pool_address": "0x811beed0119b4afce20d2583eb608c6f7af1954f",
    "pair": "SHIB / WETH",
    "price_usd": 7.17631455230371e-6,
    "lp_reserve_usd": 736463.018,
    "volume_24h": 21506.0493646929,
    "fee_tier": null,
    "source": "geckoterminal",
    "timestamp": 1767060374
  },
  {
    "symbol": "SHIB",
    "chain": "multi",
    "dex": "dinosaureggs",
    "pool_address": "0x98386f283e088ad53048376fc1c3bf2f726f775a",
    "pair": "SHIB / WBNB",
    "price_usd": 7.15475576515987e-6,
    "lp_reserve_usd": 474309.8173,
    "volume_24h": 21320.01623713,
    "fee_tier": null,
    "source": "geckoterminal",
    "timestamp": 1767060374
  },
  {
    "symbol": "SHIB",
    "chain": "solana",
    "dex": "raydium",
    "pool_address": "14bLC2KcZ2yFyCDSzHsNemoXUGf9fCmgqQ8jeHEfr3Ed",
    "pair": "SHIB/USD",
    "price_usd": 0.0002921,
    "lp_reserve_usd": 97035.98,
    "volume_24h": 1171.97,
    "fee_tier": null,
    "source": "dexscreener",
    "timestamp": 1767060374
  },
  {
    "symbol": "SHIB",
    "chain": "solana",
    "dex": "raydium",
    "pool_address": "95AnvdzmPQyRqZ4DG95cySGbs6MMWhishrWZ7fX6DNqg",
    "pair": "SHIB/USD",
    "price_usd": 0.0000119,
    "lp_reserve_usd": 182793.95,
    "volume_24h": 98165.0,
    "fee_tier": null,
    "source": "dexscreener",
    "timestamp": 1767060374
  },
  {
    "symbol": "SHIB",
    "chain": "multi",
    "dex": "raydium-clmm",
    "pool_address": "E17driKsPVYsAzSk3QnZsSVRK2TaxRHqXWRdYZtsJiCz",
    "pair": "SHIB / USDC",
    "price_usd": 7.997654077283934e-6,
    "lp_reserve_usd": 3598584.799,
    "volume_24h": 183056.718410706,
    "fee_tier": null,
    "source": "geckoterminal",
    "timestamp": 1767060374
  },
  {
    "symbol": "SHIB",
    "chain": "multi",
    "dex": "pancakeswap_v2",
    "pool_address": "0x6b7b3523a6660a5fce3c28e1536cc8dd8d57f7e0",
    "pair": "SHIB / WBNB",
    "price_usd": 7.23021064343974e-6,
    "lp_reserve_usd": 72244.5777,
    "volume_24h": 6928.5895102599,
    "fee_tier": null,
    "source": "geckoterminal",
    "timestamp": 1767046011
  },
  {
    "symbol": "SHIB",
    "chain": "multi",
    "dex": "babyswap",
    "pool_address": "0x14c594222106283dd6d155b9d00a943b94153066",
    "pair": "SHIB / USDT",
    "price_usd": 7.25881941469895e-6,
    "lp_reserve_usd": 60594.9539,
    "volume_24h": 7506.956587816,
    "fee_tier": null,
    "source": "geckoterminal",
    "timestamp": 1767035296
  },
  {
    "symbol": "SHIB",
    "chain": "solana",
    "dex": "orca",
    "pool_address": "57p4iwARAg6dXA5uB5GZnaN5StTgkEP9j7uJz1gNBBSS",
    "pair": "SHIB/USD",
    "price_usd": 0.00001326,
    "lp_reserve_usd": 118334182.7,
    "volume_24h": 3.99,
    "fee_tier": null,
    "source": "dexscreener",
    "timestamp": 1767060374
  },
  {
    "symbol": "SHIB",
    "chain": "solana",
    "dex": "raydium",
    "pool_address": "36y1LqJQNL7jPU4hUoFhGegXNQHKJggGkg5inSukRTuR",
    "pair": "SHIB/USD",
    "price_usd": 0.00002221,
    "lp_reserve_usd": 41294.76,
    "volume_24h": 71.58,
    "fee_tier": null,
    "source": "dexscreener",
    "timestamp": 1767060374
  },
  {
    "symbol": "SHIB",
    "chain": "multi",
    "dex": "apeswap_bsc",
    "pool_address": "0xc0afb6078981629f7eae4f2ae93b6dbea9d7a7e9",
    "pair": "SHIB / WBNB",
    "price_usd": 7.2589132211344e-6,
    "lp_reserve_usd": 71324.0536,
    "volume_24h": 6407.7382566475,
    "fee_tier": null,
    "source": "geckoterminal",
    "timestamp": 1767044857
  },
  {
    "symbol": "SHIB",
    "chain": "base",
    "dex": "uniswap",
    "pool_address": "0x06249abc099011fec3a5550a7a6d1f12ba90ad9b9c59cd13b32a83b5c1fad7ee",
    "pair": "SHIB/USD",
    "price_usd": 6.726e-9,
    "lp_reserve_usd": 449638.42,
    "volume_24h": 8891.32,
    "fee_tier": null,
    "source": "dexscreener",
    "timestamp": 1767060374
  },
  {
    "symbol": "SHIB",
    "chain": "multi",
    "dex": "uniswap-v4-base",
    "pool_address": "0x06249abc099011fec3a5550a7a6d1f12ba90ad9b9c59cd13b32a83b5c1fad7ee",
    "pair": "SHIB / ETH 1.99%",
    "price_usd": 6.86479003211176e-9,
    "lp_reserve_usd": 454779.029,
    "volume_24h": 8879.9147608659,
    "fee_tier": null,
    "source": "geckoterminal",
    "timestamp": 1767060374
  },
  {
    "symbol": "SHIB",
    "chain": "multi",
    "dex": "uniswap_v3",
    "pool_address": "0x2f62f2b4c5fcd7570a709dec05d68ea19c82a9ec",
    "pair": "SHIB / WETH 0.3%",
    "price_usd": 7.1690400024681e-6,
    "lp_reserve_usd": 755172.5651,
    "volume_24h": 30746.9811489902,
    "fee_tier": null,
    "source": "geckoterminal",
    "timestamp": 1767060374
  },
  {
    "symbol": "SHIB",
    "chain": "base",
    "dex": "uniswap",
    "pool_address": "0x4fbB43E487f128D3c94dC668ab5b60e0Ae9Ca001",
    "pair": "SHIB/USD",
    "price_usd": 6.832e-9,
    "lp_reserve_usd": 11951.4,
    "volume_24h": 15883.67,
    "fee_tier": null,
    "source": "dexscreener",
    "timestamp": 1767060374
  },
  {
    "symbol": "SHIB",
    "chain": "multi",
    "dex": "shibaswap",
    "pool_address": "0xcf6daab95c476106eca715d48de4b13287ffdeaa",
    "pair": "SHIB / WETH",
    "price_usd": 7.17499786976597e-6,
    "lp_reserve_usd": 3581025.8346,
    "volume_24h": 92459.0772318823,
    "fee_tier": null,
    "source": "geckoterminal",
    "timestamp": 1767060374
  },
  {
    "symbol": "SHIB",
    "chain": "base",
    "dex": "uniswap",
    "pool_address": "0x7770aec1ba4c9b247f0a0de0fba1e5fc6c6c014a1d0edd6fed001d002fec13e1",
    "pair": "SHIB/USD",
    "price_usd": 6.632e-9,
    "lp_reserve_usd": 25986.71,
    "volume_24h": 628.32,
    "fee_tier": null,
    "source": "dexscreener",
    "timestamp": 1767060374
  },
  {
    "symbol": "SHIB",
    "chain": "pulsechain",
    "dex": "pulsex",
    "pool_address": "0xe11Ae46AA5200984d59FF54F3b2c7Ff6AC6EF749",
    "pair": "SHIB/USD",
    "price_usd": 2.243e-8,
    "lp_reserve_usd": 10860.55,
    "volume_24h": 143.31,
    "fee_tier": null,
    "source": "dexscreener",
    "timestamp": 1767060374
  },
  {
    "symbol": "SHIB",
    "chain": "solana",
    "dex": "meteora",
    "pool_address": "2z4gxEu6fuFC9ijLG8mG4bh2Ptxc8M5GnzFv6Ywx1qwd",
    "pair": "SHIB/USD",
    "price_usd": 0.00001918,
    "lp_reserve_usd": 10302132.77,
    "volume_24h": 3.99,
    "fee_tier": null,
    "source": "dexscreener",
    "timestamp": 1767060374
  },
  {
    "symbol": "SHIB",
    "chain": "cronos",
    "dex": "vvsfinance",
    "pool_address": "0xc9eA98736dbC94FAA91AbF9F4aD1eb41e7fb40f4",
    "pair": "SHIB/USD",
    "price_usd": 7.181e-6,
    "lp_reserve_usd": 184395.34,
    "volume_24h": 4806.8,
    "fee_tier": null,
    "source": "dexscreener",
    "timestamp": 1767060374
  },
  {
    "symbol": "SHIB",
    "chain": "multi",
    "dex": "shibaswap",
    "pool_address": "0xff64cb7ba5717a10dabc4be3a41acd2c2f95ee22",
    "pair": "SHIB / BONE",
    "price_usd": 7.15652714297807e-6,
    "lp_reserve_usd": 341578.9486,
    "volume_24h": 3238.2853556486,
    "fee_tier": null,
    "source": "geckoterminal",
    "timestamp": 1767060374
  },
  {
    "symbol": "SHIB",
    "chain": "multi",
    "dex": "uniswap_v3",
    "pool_address": "0x5764a6f2212d502bc5970f9f129ffcd61e5d7563",
    "pair": "SHIB / WETH 1%",
    "price_usd": 7.14695715606012e-6,
    "lp_reserve_usd": 320111.7227,
    "volume_24h": 2091.2330945544,
    "fee_tier": null,
    "source": "geckoterminal",
    "timestamp": 1767060374
  }
]