[
  {
    "symbol": "TOSHI",
    "chain": "multi",
    "dex": "pancakeswap-v3-bsc",
    "pool_address": "0x27820f8b2e7c5dbe1eef6805577c222afde1a191",
    "pair": "TOSHI / USDT 0.05%",
    "price_usd": 0.000300245532574837,
    "lp_reserve_usd": 733189.4214,
    "volume_24h": 361103.154665493,
    "fee_tier": null,
    "source": "geckoterminal",
    "timestamp": 1767009780
  },
  {
    "symbol": "TOSHI",
    "chain": "multi",
    "dex": "baseswap",
    "pool_address": "0xcefb04d884c9414140286b01754126b61df6b247",
    "pair": "TOSHI / WETH",
    "price_usd": 0.000299577099749108,
    "lp_reserve_usd": 10848.8959,
    "volume_24h": 2063.4715985677,
    "fee_tier": null,
    "source": "geckoterminal",
    "timestamp": 1767009780
  },
  {
    "symbol": "TOSHI",
    "chain": "multi",
    "dex": "aerodrome-slipstream",
    "pool_address": "0x74e4c08bb50619b70550733d32b7e60424e9628e",
    "pair": "TOSHI / WETH 1%",
    "price_usd": 0.000298844004722228,
    "lp_reserve_usd": 137906.5678,
    "volume_24h": 631519.395962576,
    "fee_tier": null,
    "source": "geckoterminal",
    "timestamp": 1767009780
  },
  {
    "symbol": "TOSHI",
    "chain": "multi",
    "dex": "uniswap-v3-base",
    "pool_address": "0xfc131b9981fb053c2cab7373daf70def1436c4bb",
    "pair": "TOSHI / USDC 1%",
    "price_usd": 0.000302791019603359,
    "lp_reserve_usd": 32557.6421,
    "volume_24h": 5457.0778198886,
    "fee_tier": null,
    "source": "geckoterminal",
    "timestamp": 1767009780
  },
  {
    "symbol": "TOSHI",
    "chain": "multi",
    "dex": "uniswap-v3-base",
    "pool_address": "0x5aa4ad647580bfe86258d300bc9852f4434e2c61",
    "pair": "TOSHI / WETH 0.3%",
    "price_usd": 0.000298259950223947,
    "lp_reserve_usd": 137053.3595,
    "volume_24h": 298440.497345516,
    "fee_tier": null,
    "source": "geckoterminal",
    "timestamp": 1767009780
  },
  {
    "symbol": "TOSHI",
    "chain": "multi",
    "dex": "uniswap-v2-base",
    "pool_address": "0x368ea6f645deb6d1a8692fe93c550d2834150865",
    "pair": "TOSHI / VIRTUAL",
    "price_usd": 0.000302723663888468,
    "lp_reserve_usd": 94224.3961,
    "volume_24h": 19612.8885108168,
    "fee_tier": null,
    "source": "geckoterminal",
    "timestamp": 1767009780
  },
  {
    "symbol": "TOSHI",
    "chain": "multi",
    "dex": "uniswap-v4-base",
    "pool_address": "0xd34903c3f489aca13e44638c9248d37c1ce6569f31a83f4b8987fdb30595cc9a",
    "pair": "TOSHI / ETH 1%",
    "price_usd": 0.000300595762770289,
    "lp_reserve_usd": 47747.9912,
    "volume_24h": 2470.2830107131,
    "fee_tier": null,
    "source": "geckoterminal",
    "timestamp": 1767009780
  },
  {
    "symbol": "TOSHI",
    "chain": "multi",
    "dex": "pancakeswap-v3-bsc",
    "pool_address": "0xc0d05c35875ec95aed06db6cbb36bf32730fe67d",
    "pair": "TOSHI / USDT 0.01%",
    "price_usd": 0.000299975543439526,
    "lp_reserve_usd": 9248.7401,
    "volume_24h": 8600.8545918955,
    "fee_tier": null,
    "source": "geckoterminal",
    "timestamp": 1767009780
  },
  {
    "symbol": "TOSHI",
    "chain": "multi",
    "dex": "uniswap-v3-base",
    "pool_address": "0x4b0aaf3ebb163dd45f663b38b6d93f6093ebc2d3",
    "pair": "TOSHI / WETH 1%",
    "price_usd": 0.000300175118415755,
    "lp_reserve_usd": 2143070.5662,
    "volume_24h": 225701.504232962,
    "fee_tier": null,
    "source": "geckoterminal",
    "timestamp": 1767009780
  },
  {
    "symbol": "TOSHI",
    "chain": "multi",
    "dex": "uniswap-v2-base",
    "pool_address": "0x14098cbd08f5d61bb336312a4c2e1c2bc77bdfb5",
    "pair": "CTOSHI / WETH",
    "price_usd": 0.0000526126982712846,
    "lp_reserve_usd": 26957.0452,
    "volume_24h": 4302.4594472571,
    "fee_tier": null,
    "source": "geckoterminal",
    "timestamp": 1767009780
  }
]