[
  {
    "symbol": "WETH",
    "chain": "soneium",
    "dex": "uniswap",
    "pool_address": "0xcD4255cEAE51803a9333AA1a559991E17B024eFC",
    "pair": "WETH/USD",
    "price_usd": 2934.78,
    "lp_reserve_usd": 8266.85,
    "volume_24h": 43612.22,
    "fee_tier": null,
    "source": "dexscreener",
    "timestamp": 1767060382
  },
  {
    "symbol": "WETH",
    "chain": "linea",
    "dex": "etherex",
    "pool_address": "0xAd98EaFC5C6E2e377615A5E78Cb3f8738359D523",
    "pair": "WETH/USD",
    "price_usd": 2933.66,
    "lp_reserve_usd": 44700.06,
    "volume_24h": 408184.74,
    "fee_tier": null,
    "source": "dexscreener",
    "timestamp": 1767056471
  },
  {
    "symbol": "WETH",
    "chain": "soneium",
    "dex": "velodrome",
    "pool_address": "0x5441c4c5cc00D33bd9409F742D511Ee01db1667B",
    "pair": "WETH/USD",
    "price_usd": 2932.14,
    "lp_reserve_usd": 76671.04,
    "volume_24h": 169236.25,
    "fee_tier": null,
    "source": "dexscreener",
    "timestamp": 1767060382
  },
  {
    "symbol": "WETH",
    "chain": "celo",
    "dex": "velodrome",
    "pool_address": "0xA6A14E6767C07Ffba3786Ac0054A8647Cfdca58D",
    "pair": "WETH/USD",
    "price_usd": 2921.9,
    "lp_reserve_usd": 166005.3,
    "volume_24h": 241087.9,
    "fee_tier": null,
    "source": "dexscreener",
    "timestamp": 1767060382
  },
  {
    "symbol": "WETH",
    "chain": "solana",
    "dex": "meteora",
    "pool_address": "3potGhhaNyzvCNq1CGh2wLbZLLMjpdPtG1Hpj8q2DDVR",
    "pair": "WETH/USD",
    "price_usd": 2932.062,
    "lp_reserve_usd": 328323.7,
    "volume_24h": 932082.27,
    "fee_tier": null,
    "source": "dexscreener",
    "timestamp": 1767060382
  },
  {
    "symbol": "WETH",
    "chain": "celo",
    "dex": "uniswap",
    "pool_address": "0xF55791AfBB35aD42984f18D6Fe3e1fF73D81900c",
    "pair": "WETH/USD",
    "price_usd": 2921.41,
    "lp_reserve_usd": 316906.49,
    "volume_24h": 335277.42,
    "fee_tier": null,
    "source": "dexscreener",
    "timestamp": 1767060382
  },
  {
    "symbol": "WETH",
    "chain": "solana",
    "dex": "orca",
    "pool_address": "HktfL7iwGKT5QHjywQkcDnZXScoh811k7akrMZJkCcEF",
    "pair": "WETH/USD",
    "price_usd": 2929.34,
    "lp_reserve_usd": 6952832.96,
    "volume_24h": 20680574.46,
    "fee_tier": null,
    "source": "dexscreener",
    "timestamp": 1767060382
  },
  {
    "symbol": "WETH",
    "chain": "scroll",
    "dex": "0x1d25AF2b0992bf227b350860Ea80Bad47382CAf6",
    "pool_address": "0x04566Bf83399E4F750728d1ef57008AedDA00E71",
    "pair": "WETH/USD",
    "price_usd": 2930.95,
    "lp_reserve_usd": 976207.23,
    "volume_24h": 849461.19,
    "fee_tier": null,
    "source": "dexscreener",
    "timestamp": 1767060382
  },
  {
    "symbol": "WETH",
    "chain": "manta",
    "dex": "quickswap",
    "pool_address": "0x12CdDeD759B14bf6A34FbF6638aec9B735824a9E",
    "pair": "WETH/USD",
    "price_usd": 2933.39,
    "lp_reserve_usd": 895640.8,
    "volume_24h": 84125.7,
    "fee_tier": null,
    "source": "dexscreener",
    "timestamp": 1767060382
  },
  {
    "symbol": "WETH",
    "chain": "solana",
    "dex": "orca",
    "pool_address": "AU971DrPyhhrpRnmEBp5pDTWL2ny7nofb5vYBjDJkR2E",
    "pair": "WETH/USD",
    "price_usd": 2927.59,
    "lp_reserve_usd": 506082.07,
    "volume_24h": 867338.28,
    "fee_tier": null,
    "source": "dexscreener",
    "timestamp": 1767060382
  },
  {
    "symbol": "WETH",
    "chain": "soneium",
    "dex": "kyo-finance",
    "pool_address": "0x30f4fddb02a82076694682DCC9FC92e3AeCFf99c",
    "pair": "WETH/USD",
    "price_usd": 2931.5,
    "lp_reserve_usd": 101185.96,
    "volume_24h": 126589.84,
    "fee_tier": null,
    "source": "dexscreener",
    "timestamp": 1767060382
  }
]